{
  "run_id": "2026-03-02_23-45-42",
  "scope": "Create a Python script named 'hello_world.py' that prints the text 'Hello, World!' to the console when executed.",
  "tasks": [
    {
      "id": "task_1",
      "title": "Implement hello_world.py script",
      "description": "Create a Python file named 'hello_world.py'. Implement a single function or method that prints 'Hello, World!' to the console using print(). Ensure the script runs this function when executed. Tests: Run the script and verify it outputs 'Hello, World!'.",
      "dependencies": []
    }
  ],
  "task_summaries": [
    "\u2713 task_1: Implement hello_world.py script (1 iter)"
  ],
  "metrics": {
    "tasks_total": 1,
    "tasks_passed": 1,
    "tasks_failed": 0,
    "approval_rate": 1.0,
    "agent_metrics": {
      "coder": {
        "tasks_attempted": 1,
        "tasks_approved": 1,
        "approval_rate": 1.0,
        "avg_iterations": 1.0,
        "empty_outputs": 0,
        "already_done_count": 0
      },
      "reviewer": {
        "tasks_attempted": 1,
        "tasks_approved": 1,
        "approval_rate": 1.0,
        "avg_iterations": 1.0,
        "empty_outputs": 0,
        "already_done_count": 0
      }
    }
  },
  "timestamp": 1772491665.4870393
}